EasyDAG_Web/__init__.py
EasyDAG_Web/bus.py
EasyDAG_Web/emitter.py
easydag_web-0.1.3.dist-info/METADATA
easydag_web-0.1.3.dist-info/WHEEL
easydag_web-0.1.3.dist-info/licenses/LICENSE
easydag_web-0.1.3.dist-info/RECORD
