Metadata-Version: 2.3
Name: EasyDAG-Web
Version: 0.1.3
Summary: A small EasyDAG extension with predefined websocket setup for API usage.
Project-URL: Homepage, https://github.com/mechatronicist/EasyDAG-Web
Project-URL: Repository, https://github.com/mechatronicist/EasyDAG-Web
Project-URL: Issues, https://github.com/mechatronicist/EasyDAG-Web/issues
Author: Mechatronicist
License: MIT License
Keywords: api,dag,multiprocessing,parallel,tasks,web,workflow
Requires-Python: >=3.9
Requires-Dist: easydag
